cufflinks/__init__.py
cufflinks/auth.py
cufflinks/colors.py
cufflinks/datagen.py
cufflinks/date_tools.py
cufflinks/exceptions.py
cufflinks/extract.py
cufflinks/helper.py
cufflinks/offline.py
cufflinks/pandastools.py
cufflinks/plotlytools.py
cufflinks/quant_figure.py
cufflinks/ta.py
cufflinks/themes.py
cufflinks/tools.py
cufflinks/utils.py
cufflinks/version.py
helper/params.json
cufflinks_ardihikaru-0.17.5.dist-info/METADATA
cufflinks_ardihikaru-0.17.5.dist-info/WHEEL
cufflinks_ardihikaru-0.17.5.dist-info/top_level.txt
cufflinks_ardihikaru-0.17.5.dist-info/RECORD
