Metadata-Version: 2.1
Name: cufflinks-ardihikaru
Version: 0.17.5
Summary: Productivity Tools for Plotly + Pandas
Home-page: https://github.com/santosjorge/cufflinks
Author: Jorge Santos (adjusted by Muhammad Febrian Ardiansyah)
Author-email: santos.jorge@gmail.com
License: MIT
Keywords: pandas,plotly,plotting
Classifier: Programming Language :: Python
Classifier: Programming Language :: Python :: 2
Classifier: Programming Language :: Python :: 3
Requires-Dist: numpy ==1.21.4
Requires-Dist: pandas ==2.0.3
Requires-Dist: pandas-ta ==0.3.14b0
Requires-Dist: plotly ==5.16.1
Requires-Dist: six ==1.16.0
Requires-Dist: colorlover ==0.3.0
Requires-Dist: setuptools >=34.4.1
Requires-Dist: ipython >=5.3.0
Requires-Dist: ipywidgets >=7.0.0
Requires-Dist: nbformat ==5.9.2
